<?xml version="1.0" encoding="utf-8" ?>
<dwsync>
<file name="add.gif" server="aricimdan.com//public_html/" local="131941753841426475" remote="131454036000000000" Dst="0" />
<file name="clear_basket.gif" server="aricimdan.com//public_html/" local="131941753841466406" remote="131454036000000000" Dst="0" />
<file name="delete.gif" server="aricimdan.com//public_html/" local="131941753844966027" remote="131454036000000000" Dst="0" />
<file name="download.gif" server="aricimdan.com//public_html/" local="131941753845045731" remote="131454036000000000" Dst="0" />
<file name="help.gif" server="aricimdan.com//public_html/" local="131941753845085761" remote="131454036000000000" Dst="0" />
<file name="maximize.gif" server="aricimdan.com//public_html/" local="131941753848605382" remote="131454036000000000" Dst="0" />
<file name="refresh.gif" server="aricimdan.com//public_html/" local="131941753848684866" remote="131454036000000000" Dst="0" />
<file name="settings.gif" server="aricimdan.com//public_html/" local="131941753848724826" remote="131454036000000000" Dst="0" />
<file name="view.gif" server="aricimdan.com//public_html/" local="131941753852764323" remote="131454036000000000" Dst="0" />
<file name="add.gif" server="94.73.144.214//public_html/" local="132019712997627223" remote="131454036000000000" Dst="0" />
<file name="clear_basket.gif" server="94.73.144.214//public_html/" local="132019712999658259" remote="131454036000000000" Dst="0" />
<file name="download.gif" server="94.73.144.214//public_html/" local="132019712999698404" remote="131454036000000000" Dst="0" />
<file name="delete.gif" server="94.73.144.214//public_html/" local="132019712999698404" remote="131454036000000000" Dst="0" />
<file name="help.gif" server="94.73.144.214//public_html/" local="132019713001987371" remote="131454036000000000" Dst="0" />
<file name="maximize.gif" server="94.73.144.214//public_html/" local="132019713002007355" remote="131454036000000000" Dst="0" />
<file name="refresh.gif" server="94.73.144.214//public_html/" local="132019713002107295" remote="131454036000000000" Dst="0" />
<file name="settings.gif" server="94.73.144.214//public_html/" local="132019713004487760" remote="131454036000000000" Dst="0" />
<file name="view.gif" server="94.73.144.214//public_html/" local="132019713004497772" remote="131454036000000000" Dst="0" />
</dwsync>