<?xml version="1.0" encoding="utf-8" ?>
<dwsync>
<file name="animated.less" server="aricimdan.com//public_html/" local="131941768558164179" remote="131479092000000000" Dst="0" />
<file name="bordered-pulled.less" server="aricimdan.com//public_html/" local="131941768558284135" remote="131479092000000000" Dst="0" />
<file name="core.less" server="aricimdan.com//public_html/" local="131941768565685638" remote="131479092000000000" Dst="0" />
<file name="fixed-width.less" server="aricimdan.com//public_html/" local="131941768565765580" remote="131479092000000000" Dst="0" />
<file name="font-awesome.less" server="aricimdan.com//public_html/" local="131941768574489702" remote="131479092000000000" Dst="0" />
<file name="larger.less" server="aricimdan.com//public_html/" local="131941768574609905" remote="131479092000000000" Dst="0" />
<file name="icons.less" server="aricimdan.com//public_html/" local="131941768574809627" remote="131479092000000000" Dst="0" />
<file name="list.less" server="aricimdan.com//public_html/" local="131941768579844616" remote="131479092000000000" Dst="0" />
<file name="mixins.less" server="aricimdan.com//public_html/" local="131941768579979829" remote="131479092000000000" Dst="0" />
<file name="path.less" server="aricimdan.com//public_html/" local="131941768580259736" remote="131479092000000000" Dst="0" />
<file name="rotated-flipped.less" server="aricimdan.com//public_html/" local="131941768585720499" remote="131479092000000000" Dst="0" />
<file name="screen-reader.less" server="aricimdan.com//public_html/" local="131941768585840383" remote="131479092000000000" Dst="0" />
<file name="stacked.less" server="aricimdan.com//public_html/" local="131941768585981108" remote="131479092000000000" Dst="0" />
<file name="variables.less" server="aricimdan.com//public_html/" local="131941768593225242" remote="131479092000000000" Dst="0" />
</dwsync>